[ 
{"Id": 1,"Name": "Aarau"}, 
{"Id": 2,"Name": "Altdorf"}, 
{"Id": 3,"Name": "Appenzell"}, 
{"Id": 4,"Name": "Basel"}, 
{"Id": 5,"Name": "Bellinzona"}, 
{"Id": 6,"Name": "Bern"}, 
{"Id": 7,"Name": "Biel"}, 
{"Id": 8,"Name": "Chur"}, 
{"Id": 9,"Name": "Delémont"}, 
{"Id": 10,"Name": "Frauenfeld"}, 
{"Id": 11,"Name": "Fribourg"}, 
{"Id": 12,"Name": "Geneva"}, 
{"Id": 13,"Name": "Glarus"}, 
{"Id": 14,"Name": "Herisau"}, 
{"Id": 15,"Name": "Lausanne"}, 
{"Id": 16,"Name": "Liestal"}, 
{"Id": 17,"Name": "Lugano"}, 
{"Id": 18,"Name": "Luzern"}, 
{"Id": 19,"Name": "Neuchâtel"}, 
{"Id": 20,"Name": "Saint"}, 
{"Id": 21,"Name": "Sarnen"}, 
{"Id": 22,"Name": "Schaffhausen"}, 
{"Id": 23,"Name": "Schwyz"}, 
{"Id": 24,"Name": "Sion"}, 
{"Id": 25,"Name": "Solothurn"}, 
{"Id": 26,"Name": "Stans"}, 
{"Id": 27,"Name": "Zürich"}, 
{"Id": 28,"Name": "Zug"} 
] 
